sayminimal/__init__.py
sayminimal/toot.py
sayminimal/v4.glade
sayminimal-4.0.0.dist-info/LICENSE
sayminimal-4.0.0.dist-info/METADATA
sayminimal-4.0.0.dist-info/WHEEL
sayminimal-4.0.0.dist-info/entry_points.txt
sayminimal-4.0.0.dist-info/top_level.txt
sayminimal-4.0.0.dist-info/RECORD
