Metadata-Version: 2.1
Name: sayminimal
Version: 4.0.0
Summary: A minimalist write-only Mastodon client.
Home-page: https://github.com/mduo13/sayminimal
Author: mDuo13
Author-email: mduo13@gmail.com
License: GPLv3
Keywords: mastodon social microblogging
Classifier: Development Status :: 3 - Alpha
Classifier: Environment :: X11 Applications :: GTK
Classifier: Intended Audience :: End Users/Desktop
Classifier: License :: OSI Approved :: GNU General Public License v3 (GPLv3)
Classifier: Operating System :: POSIX
Classifier: Programming Language :: Python :: 3
Classifier: Programming Language :: Python :: 3.7
Classifier: Programming Language :: Python :: 3.8
Classifier: Programming Language :: Python :: 3.9
Classifier: Programming Language :: Python :: 3.10
Classifier: Topic :: Communications
License-File: LICENSE
Requires-Dist: PyYAML
Requires-Dist: Mastodon.py
